aitemplates/__init__.py
aitemplates/cells.py
aitemplates/main.py
aitemplates/oai/__init__.py
aitemplates/oai/ApiManager.py
aitemplates/oai/responses/__init__.py
aitemplates/oai/responses/async_chat_response.py
aitemplates/oai/responses/chat_response.py
aitemplates/oai/responses/embedding.py
aitemplates/oai/types/__init__.py
aitemplates/oai/types/base.py
aitemplates/oai/types/chat.py
aitemplates/oai/types/functions.py
aitemplates/oai/types/models.py
aitemplates/oai/types/Singleton.py
aitemplates/oai/utils/__init__.py
aitemplates/oai/utils/count_tokens.py
aitemplates/oai/utils/wrappers.py
aitemplates-0.1.28.dist-info/entry_points.txt
aitemplates-0.1.28.dist-info/LICENSE
aitemplates-0.1.28.dist-info/METADATA
aitemplates-0.1.28.dist-info/WHEEL
aitemplates-0.1.28.dist-info/RECORD
