Metadata-Version: 2.1
Name: aitemplates
Version: 0.1.28
Summary: Designed to streamline and simplify your AI workflows, it offers Python typing support, error checking, and a smart usage meter to manage API costs efficiently. Plus, it features built-in examples with ChromaDB and efficient tools for prompt engineering.
Author: Silen Naihin
Author-email: silen.naihin@gmail.com
Requires-Python: >=3.9,<4.0
Classifier: Programming Language :: Python :: 3
Classifier: Programming Language :: Python :: 3.9
Classifier: Programming Language :: Python :: 3.10
Classifier: Programming Language :: Python :: 3.11
Requires-Dist: aiohttp (>=3.8.4,<4.0.0)
Requires-Dist: aiolimiter (>=1.1.0,<2.0.0)
Requires-Dist: argparse (>=1.4.0,<2.0.0)
Requires-Dist: chromadb (>=0.3.26,<0.4.0)
Requires-Dist: jsonschema (>=4.17.3,<5.0.0)
Requires-Dist: nbformat (>=5.9.0,<6.0.0)
Requires-Dist: openai (>=0.27.8,<0.28.0)
Requires-Dist: pydantic (>=1.10.9,<2.0.0)
Requires-Dist: termcolor (>=2.3.0,<3.0.0)
